microstructpy/__init__.py
microstructpy/_misc.py
microstructpy/cli.py
microstructpy/verification.py
microstructpy/examples/aluminum_micro.png
microstructpy/examples/aphanitic_cdf.csv
microstructpy/examples/basalt_circle.xml
microstructpy/examples/colormap.xml
microstructpy/examples/docs_banner.py
microstructpy/examples/elliptical_grains.xml
microstructpy/examples/foam.py
microstructpy/examples/from_image.py
microstructpy/examples/grain_neighborhoods.py
microstructpy/examples/intro_1_basic.xml
microstructpy/examples/intro_2_quality.xml
microstructpy/examples/intro_3_size_shape.xml
microstructpy/examples/intro_4_oriented.xml
microstructpy/examples/intro_5_plotting.xml
microstructpy/examples/intro_6_culmination.xml
microstructpy/examples/logo.py
microstructpy/examples/minimal.xml
microstructpy/examples/minimal_paired.xml
microstructpy/examples/olivine_cdf.csv
microstructpy/examples/standard_voronoi.py
microstructpy/examples/two_phase_3D.xml
microstructpy/examples/uniform_seeding.py
microstructpy/geometry/__init__.py
microstructpy/geometry/box.py
microstructpy/geometry/circle.py
microstructpy/geometry/ellipse.py
microstructpy/geometry/ellipsoid.py
microstructpy/geometry/n_box.py
microstructpy/geometry/n_sphere.py
microstructpy/geometry/rectangle.py
microstructpy/geometry/sphere.py
microstructpy/meshing/__init__.py
microstructpy/meshing/polymesh.py
microstructpy/meshing/trimesh.py
microstructpy/seeding/__init__.py
microstructpy/seeding/seed.py
microstructpy/seeding/seedlist.py
microstructpy-1.5.9.dist-info/LICENSE.rst
microstructpy-1.5.9.dist-info/METADATA
microstructpy-1.5.9.dist-info/WHEEL
microstructpy-1.5.9.dist-info/entry_points.txt
microstructpy-1.5.9.dist-info/top_level.txt
microstructpy-1.5.9.dist-info/RECORD
