Metadata-Version: 2.1
Name: microstructpy
Version: 1.5.9
Summary: Microstructure modeling, mesh generation, analysis, and visualization.
Home-page: https://github.com/kip-hart/MicroStructPy
Author: Kenneth (Kip) Hart
Author-email: kiphart91@gmail.com
License: MIT License
Project-URL: Documentation, https://docs.microstructpy.org
Keywords: microstructure,micromechanics,finite element,FEM,FEA,mesh,polycrystal,tessellation,Laguerre tessellation,multi-sphere
Classifier: Development Status :: 4 - Beta
Classifier: Intended Audience :: Science/Research
Classifier: License :: OSI Approved :: MIT License
Classifier: Operating System :: MacOS :: MacOS X
Classifier: Operating System :: Microsoft :: Windows
Classifier: Operating System :: POSIX :: Linux
Classifier: Programming Language :: Python :: 3.8
Classifier: Programming Language :: Python :: 3.9
Classifier: Programming Language :: Python :: 3.10
Classifier: Programming Language :: Python :: 3.11
Classifier: Programming Language :: Python :: 3.12
Classifier: Topic :: Scientific/Engineering
Classifier: Topic :: Scientific/Engineering :: Mathematics
Classifier: Topic :: Scientific/Engineering :: Physics
License-File: LICENSE.rst
Requires-Dist: aabbtree >=2.5.0
Requires-Dist: pybind11
Requires-Dist: lsq-ellipse
Requires-Dist: matplotlib >=3.4.0
Requires-Dist: meshpy >=2018.2.1
Requires-Dist: numpy >=1.22.2
Requires-Dist: pygmsh >=7.0.2
Requires-Dist: pyquaternion
Requires-Dist: pyvoro-mmalahe >=1.3.4
Requires-Dist: scipy
Requires-Dist: xmltodict
